StrongJWT/StrongJWT.py
StrongJWT/__init__.py
StrongJWT-0.0.4.dist-info/LICENSE
StrongJWT-0.0.4.dist-info/METADATA
StrongJWT-0.0.4.dist-info/WHEEL
StrongJWT-0.0.4.dist-info/top_level.txt
StrongJWT-0.0.4.dist-info/RECORD
