Metadata-Version: 2.1
Name: StrongJWT
Version: 0.0.4
Summary: Python library to validate JWTs.
Author: Tony Guimelli
Author-email: tony.guimelli@gmail.com
License: MIT
Keywords: conversion
Classifier: Development Status :: 3 - Alpha
Classifier: Intended Audience :: Developers
Classifier: License :: OSI Approved :: MIT License
Classifier: Programming Language :: Python :: 3
License-File: LICENSE
Requires-Dist: PyJWT
Requires-Dist: requests
